LICENSE
MANIFEST.in
setup.py
cilantro/__init__.py
cilantro/admin.py
cilantro/context_processors.py
cilantro/managers.py
cilantro/models.py
cilantro/urls.py
cilantro/views.py
cilantro.egg-info/PKG-INFO
cilantro.egg-info/SOURCES.txt
cilantro.egg-info/dependency_links.txt
cilantro.egg-info/requires.txt
cilantro.egg-info/top_level.txt
cilantro/migrations/0001_initial.py
cilantro/migrations/0002_auto__add_field_siteconfiguration_auth_required.py
cilantro/migrations/0003_auto__chg_field_siteconfiguration_site.py
cilantro/migrations/__init__.py
cilantro/static/cilantro/images/chosen-sprite.png
cilantro/static/cilantro/images/fabric_plaid.png
cilantro/static/cilantro/images/loader-tiny.gif
cilantro/static/cilantro/scripts/javascript/app.build.js
cilantro/static/cilantro/scripts/javascript/min/backbone.js
cilantro/static/cilantro/scripts/javascript/min/build.txt
cilantro/static/cilantro/scripts/javascript/min/channels.js
cilantro/static/cilantro/scripts/javascript/min/charts.js
cilantro/static/cilantro/scripts/javascript/min/environ.js
cilantro/static/cilantro/scripts/javascript/min/highcharts.js
cilantro/static/cilantro/scripts/javascript/min/jquery.js
cilantro/static/cilantro/scripts/javascript/min/main.js
cilantro/static/cilantro/scripts/javascript/min/mediator.js
cilantro/static/cilantro/scripts/javascript/min/modernizr.js
cilantro/static/cilantro/scripts/javascript/min/require.js
cilantro/static/cilantro/scripts/javascript/min/router.js
cilantro/static/cilantro/scripts/javascript/min/serrano.js
cilantro/static/cilantro/scripts/javascript/min/session.js
cilantro/static/cilantro/scripts/javascript/min/underscore.js
cilantro/static/cilantro/scripts/javascript/min/behavior/pending-requests.js
cilantro/static/cilantro/scripts/javascript/min/behavior/staff-only.js
cilantro/static/cilantro/scripts/javascript/min/charts/backbone-charts.js
cilantro/static/cilantro/scripts/javascript/min/charts/models.js
cilantro/static/cilantro/scripts/javascript/min/charts/options.js
cilantro/static/cilantro/scripts/javascript/min/charts/utils.js
cilantro/static/cilantro/scripts/javascript/min/charts/views.js
