Metadata-Version: 1.0
Name: cilantro
Version: 2.0.11
Summary: A client implementation for Serrano 2.x
Home-page: http://cbmi.github.com/cilantro
Author: Byron Ruth
Author-email: b@devel.io
License: BSD
Keywords: harvest serrano client avocado
Platform: UNKNOWN
Classifier: Development Status :: 4 - Beta
Classifier: License :: OSI Approved :: BSD License
Classifier: Programming Language :: Python :: 2.6
Classifier: Programming Language :: Python :: 2.7
Classifier: Framework :: Django
Classifier: Topic :: Internet :: WWW/HTTP
Classifier: Intended Audience :: Developers
Classifier: Intended Audience :: Science/Research
Classifier: Intended Audience :: Healthcare Industry
Classifier: Intended Audience :: Information Technology
